lazyinput/__init__.py
lazyinput/main.py
lazyinput-0.1.1.dist-info/LICENSE
lazyinput-0.1.1.dist-info/METADATA
lazyinput-0.1.1.dist-info/WHEEL
lazyinput-0.1.1.dist-info/top_level.txt
lazyinput-0.1.1.dist-info/RECORD
