Metadata-Version: 2.2
Name: lazyinput
Version: 0.1.1
Summary: I am very lazy
Home-page: https://github.com/justin-huiyun-lee/
Author: 5nsou
Author-email: justin.huiyun.lee@gmail.com
License-File: LICENSE
Dynamic: author
Dynamic: author-email
Dynamic: home-page
Dynamic: summary
